stock_open_api/__init__.py
stock_open_api/log.py
stock_open_api/version.py
stock_open_api/api/__init__.py
stock_open_api/api/bse/__init__.py
stock_open_api/api/eastmoney/__init__.py
stock_open_api/api/eastmoney/company.py
stock_open_api/api/eastmoney/company_config.py
stock_open_api/api/eastmoney/hk_stock.py
stock_open_api/api/eastmoney/hk_stock_config.py
stock_open_api/api/eastmoney/kcb_stock.py
stock_open_api/api/eastmoney/kcb_stock_config.py
stock_open_api/api/eastmoney/neeq_stock.py
stock_open_api/api/eastmoney/neeq_stock_config.py
stock_open_api/api/eastmoney/sh_stock.py
stock_open_api/api/eastmoney/sz_stock.py
stock_open_api/api/eastmoney/us_chinese_stock.py
stock_open_api/api/eastmoney/us_chinese_stock_config.py
stock_open_api/api/ipo3/__init__.py
stock_open_api/api/ipo3/config.py
stock_open_api/api/ipo3/neeq_stock.py
stock_open_api/api/jqka/__init__.py
stock_open_api/api/jqka/company.py
stock_open_api/api/sse/__init__.py
stock_open_api/api/sse/sh_stock.py
stock_open_api/api/sse/sh_stock_config.py
stock_open_api/api/szse/__init__.py
stock_open_api/api/szse/sz_stock.py
stock_open_api/items/__init__.py
stock_open_api/items/list_item.py
stock_open_api/utils/__init__.py
stock_open_api/utils/convert_util.py
stock_open_api/utils/excel_util.py
stock_open_api/utils/iterator_util.py
stock_open_api/utils/json_util.py
stock_open_api/utils/request_util.py
stock_open_api/utils/table_util.py
stock_open_api/utils/time_util.py
stock_open_api/utils/ua_util.py
tests/__init__.py
tests/test_hello.py
tests/api/__init__.py
tests/api/ipo3/__init__.py
tests/api/ipo3/neeq_stock_test.py
tests/api/jqka/__init__.py
tests/api/jqka/test_company.py
tests/utils/__init__.py
tests/utils/test_iterator_util.py
stock_open_api-1.0.6.dist-info/METADATA
stock_open_api-1.0.6.dist-info/WHEEL
stock_open_api-1.0.6.dist-info/top_level.txt
stock_open_api-1.0.6.dist-info/zip-safe
stock_open_api-1.0.6.dist-info/RECORD
